uatg/__init__.py
uatg/instruction_constants.py
uatg/instruction_generator.py
uatg/isem.yaml
uatg/log.py
uatg/main.py
uatg/regex_formats.py
uatg/requirements.txt
uatg/test_generator.py
uatg/utils.py
uatg/env/arch_test_priv.h
uatg/env/arch_test_unpriv.h
uatg/env/encoding.h
uatg-1.14.0.dist-info/LICENSE.incore
uatg-1.14.0.dist-info/METADATA
uatg-1.14.0.dist-info/WHEEL
uatg-1.14.0.dist-info/entry_points.txt
uatg-1.14.0.dist-info/top_level.txt
uatg-1.14.0.dist-info/RECORD
