Metadata-Version: 2.1
Name: uatg
Version: 1.14.0
Summary: UATG - Micro-Architecture (µArch) Tests Generator
Home-page: https://github.com/incoresemi/uatg
Author: InCore Semiconductors Pvt. Ltd.
Author-email: neelgala@incoresemi.com
License: BSD-3-Clause
Keywords: uatg
Platform: UNKNOWN
Classifier: Programming Language :: Python :: 3.7
Classifier: License :: OSI Approved :: BSD License
Classifier: Development Status :: 3 - Alpha
Requires-Python: >=3.7.0
Requires-Dist: click >=7.0.0
Requires-Dist: colorlog >=5.0.1
Requires-Dist: ruamel.yaml >=0.17.16
Requires-Dist: yapsy >=1.12.2
Requires-Dist: python-constraint ==1.4.0
